README
setup.py
Spamalot.egg-info/PKG-INFO
Spamalot.egg-info/SOURCES.txt
Spamalot.egg-info/dependency_links.txt
Spamalot.egg-info/requires.txt
Spamalot.egg-info/top_level.txt
spamalot/__init__.py
spamalot/base.py
spamalot/config.py
spamalot/spammer.py
spamalot/utils.py