Metadata-Version: 1.0
Name: Spamalot
Version: 0.0.3
Summary: Python simple mailer
Home-page: http://hg.tastybra.in/public/spamalot
Author: Alberto Granzotto (vrde)
Author-email: agranzot@gmail.com
License: UNKNOWN
Platform: UNKNOWN
